btgPy/__init__.py
btgPy/btgLab.py
btgPy/CHAID/__init__.py
btgPy/CHAID/__main__.py
btgPy/CHAID/column.py
btgPy/CHAID/graph.py
btgPy/CHAID/invalid_split_reason.py
btgPy/CHAID/mapping_dict.py
btgPy/CHAID/node.py
btgPy/CHAID/split.py
btgPy/CHAID/stats.py
btgPy/CHAID/tree.py
btgPy/NeuralNetwork/Activations.py
btgPy/NeuralNetwork/Layer.py
btgPy/NeuralNetwork/Losses.py
btgPy/NeuralNetwork/MultiLayerPerceptron.py
btgPy/NeuralNetwork/__init__.py
btgPy/Testing/HypoTest.py
btgPy/Testing/TailRes.py
btgPy/Testing/__init__.py
btgPy/btgCHAID/__init__.py
btgPy/btgCHAID/__main__.py
btgPy/btgCHAID/column.py
btgPy/btgCHAID/graph.py
btgPy/btgCHAID/invalid_split_reason.py
btgPy/btgCHAID/mapping_dict.py
btgPy/btgCHAID/node.py
btgPy/btgCHAID/split.py
btgPy/btgCHAID/stats.py
btgPy/btgCHAID/tree.py
btgPy-1.0.3.dist-info/LICENSE.txt
btgPy-1.0.3.dist-info/METADATA
btgPy-1.0.3.dist-info/WHEEL
btgPy-1.0.3.dist-info/top_level.txt
btgPy-1.0.3.dist-info/RECORD
