Metadata-Version: 2.1
Name: btgPy
Version: 1.0.3
Summary: Data science tools
Home-page: https://github.com/bgonzalezd/btgPy
Author: Briter Gonzalez
Author-email: btg.developers@gmail.com
License: MIT License
Keywords: CHAID pandas numpy scipy statistics statistical analysis
Platform: UNKNOWN
Classifier: Development Status :: 5 - Production/Stable
Classifier: Intended Audience :: Developers
Classifier: Topic :: Software Development :: Build Tools
Classifier: License :: OSI Approved :: Apache Software License
Classifier: Programming Language :: Python :: 2.7
Classifier: Programming Language :: Python :: 3.5
Classifier: Programming Language :: Python :: 3.6
Requires-Dist: cython
Requires-Dist: numpy
Requires-Dist: pandas
Requires-Dist: treelib
Requires-Dist: pytest
Requires-Dist: scipy
Requires-Dist: savReaderWriter
Requires-Dist: graphviz
Requires-Dist: plotly
Requires-Dist: colorlover
Requires-Dist: enum34 ; python_version == "2.7"
Provides-Extra: test
Requires-Dist: codecov ; extra == 'test'
Requires-Dist: tox ; extra == 'test'
Requires-Dist: tox-pyenv ; extra == 'test'
Requires-Dist: detox ; extra == 'test'
Requires-Dist: pytest ; extra == 'test'
Requires-Dist: pytest-cov ; extra == 'test'
